ipo/__init__.py
ipo/ipo.py
ipo-2.0.0.dist-info/COPYING
ipo-2.0.0.dist-info/COPYING.LESSER
ipo-2.0.0.dist-info/METADATA
ipo-2.0.0.dist-info/WHEEL
ipo-2.0.0.dist-info/top_level.txt
ipo-2.0.0.dist-info/RECORD
