Metadata-Version: 2.1
Name: ipo
Version: 2.0.0
Summary: Infix piping operator
Home-page: https://framagit.org/Midgard/ipo
Author: Midgard
Project-URL: Source, https://framagit.org/Midgard/ipo
Project-URL: Change log, https://framagit.org/Midgard/ipo/-/blob/master/CHANGELOG.md
Project-URL: Bug tracker, https://framagit.org/Midgard/ipo/-/issues
Classifier: Programming Language :: Python :: 3
Classifier: License :: OSI Approved :: GNU Lesser General Public License v3 or later (LGPLv3+)
Classifier: Operating System :: OS Independent
Classifier: Intended Audience :: Developers
Classifier: Development Status :: 3 - Alpha
Classifier: Topic :: Software Development :: Libraries :: Python Modules
Requires-Python: >=3.8
License-File: COPYING
License-File: COPYING.LESSER
